README
setup.cfg
setup.py
secobj/__init__.py
secobj/action.py
secobj/config.py
secobj/decorator.py
secobj/exceptions.py
secobj/localization.py
secobj/logger.py
secobj/memoizer.py
secobj/permission.py
secobj/principal.py
secobj/rule.py
secobj/storage.py
secobj/utils.py
secobj.egg-info/PKG-INFO
secobj.egg-info/SOURCES.txt
secobj.egg-info/dependency_links.txt
secobj.egg-info/entry_points.txt
secobj.egg-info/not-zip-safe
secobj.egg-info/top_level.txt
secobj/provider/__init__.py
secobj/provider/base.py
secobj/provider/default.py
secobj/provider/unix.py