Metadata-Version: 1.1
Name: secobj
Version: 0.2a-1
Summary: ACL security for functions and classes
Home-page: https://github.com/cramren/secobj
Author: Marc Göldner
Author-email: info@cramren.de
License: GPL
Keywords: acl authorization security access
Platform: UNKNOWN
Classifier: Development Status :: 3 - Alpha
Classifier: Intended Audience :: Developers
Classifier: License :: OSI Approved :: GNU General Public License (GPL)
Classifier: Operating System :: OS Independent
Classifier: Programming Language :: Python :: 2
Classifier: Topic :: Security
Classifier: Topic :: Software Development :: Libraries
